solentware_misc/__init__.py
solentware_misc/core/__init__.py
solentware_misc/core/callthreadqueue.py
solentware_misc/core/configuration.py
solentware_misc/core/getconfigurationitem.py
solentware_misc/core/indexmap.py
solentware_misc/core/null.py
solentware_misc/core/utilities.py
solentware_misc/gui/__init__.py
solentware_misc/gui/colourslider.py
solentware_misc/gui/configuredialog.py
solentware_misc/gui/dialogue.py
solentware_misc/gui/fontchooser.py
solentware_misc/gui/frame.py
solentware_misc/gui/help_.py
solentware_misc/gui/logpanel.py
solentware_misc/gui/logtextbase.py
solentware_misc/gui/panel.py
solentware_misc/gui/reports.py
solentware_misc/gui/startstop.py
solentware_misc/gui/tasklog.py
solentware_misc/gui/textentry.py
solentware_misc/gui/textreadonly.py
solentware_misc/gui/texttab.py
solentware_misc/gui/threadqueue.py
solentware_misc/workarounds/__init__.py
solentware_misc/workarounds/dialogues.py
solentware_misc/workarounds/workarounds.py
solentware_misc-1.7.1.dist-info/LICENCE
solentware_misc-1.7.1.dist-info/METADATA
solentware_misc-1.7.1.dist-info/WHEEL
solentware_misc-1.7.1.dist-info/top_level.txt
solentware_misc-1.7.1.dist-info/RECORD
