Metadata-Version: 2.1
Name: solentware-misc
Version: 1.7.1
Summary: Classes perhaps useful beyond original application.
Author-email: Roger Marsh <roger.marsh@solentware.co.uk>
License: Licence for rmappsup package
Project-URL: Homepage, http://www.solentware.co.uk
Project-URL: Repository, https://github.com/RogerMarsh/solentware-misc.git
Project-URL: Bug Tracker, https://github.com/RogerMarsh/solentware-misc/issues
Classifier: License :: OSI Approved :: BSD License
Classifier: Programming Language :: Python :: 3.9
Classifier: Programming Language :: Python :: 3.10
Classifier: Programming Language :: Python :: 3.11
Classifier: Programming Language :: Python :: 3.12
Classifier: Operating System :: OS Independent
Classifier: Topic :: Software Development
Classifier: Intended Audience :: Developers
Classifier: Development Status :: 3 - Alpha
License-File: LICENCE
Requires-Dist: solentware-bind==1.0.2
